{
    "aries": {
      "name": "Aries",
      "description": "Aries are bold and ambitious.",
      "image": "https://storage.googleapis.com/a1aa/image/Bv76HNlgd9L7UeDoDuJ8OuVAMCYfh2-Om3GEeMMviv4.jpg"
    },
    "taurus": {
      "name": "Taurus",
      "description": "Taurus are reliable and patient.",
      "image": "https://storage.googleapis.com/a1aa/image/LTrjEyip6W8uJ7x0AmFNjlru57rWqw10KEO8R5o_zlw.jpg"
    },
    "gemini": {
      "name": "Gemini",
      "description": "Geminis are adaptable and outgoing.",
      "image": "https://storage.googleapis.com/a1aa/image/5tnFUtxyet0FyHgUEb0mpPfM2ZzOEo2_tByTDqz3yB4.jpg"
    }
  }
  